odoo/addons/calendar_monthly_multi/README.rst
odoo/addons/calendar_monthly_multi/__init__.py
odoo/addons/calendar_monthly_multi/__manifest__.py
odoo/addons/calendar_monthly_multi/data/calendar_recurrence_day_data.xml
odoo/addons/calendar_monthly_multi/data/calendar_recurrence_weekday_data.xml
odoo/addons/calendar_monthly_multi/i18n/calendar_monthly_multi.pot
odoo/addons/calendar_monthly_multi/i18n/it.po
odoo/addons/calendar_monthly_multi/models/__init__.py
odoo/addons/calendar_monthly_multi/models/calendar_event.py
odoo/addons/calendar_monthly_multi/models/calendar_recurrence.py
odoo/addons/calendar_monthly_multi/models/calendar_recurrence_day.py
odoo/addons/calendar_monthly_multi/models/calendar_recurrence_weekday.py
odoo/addons/calendar_monthly_multi/readme/CONTRIBUTORS.md
odoo/addons/calendar_monthly_multi/readme/DESCRIPTION.md
odoo/addons/calendar_monthly_multi/readme/USAGE.md
odoo/addons/calendar_monthly_multi/security/ir_model_access.xml
odoo/addons/calendar_monthly_multi/static/description/icon.png
odoo/addons/calendar_monthly_multi/static/description/index.html
odoo/addons/calendar_monthly_multi/static/description/multiple-dates.png
odoo/addons/calendar_monthly_multi/static/description/weekday-weekendday.png
odoo/addons/calendar_monthly_multi/static/src/scss/backend.scss
odoo/addons/calendar_monthly_multi/tests/__init__.py
odoo/addons/calendar_monthly_multi/tests/test_recurrence.py
odoo/addons/calendar_monthly_multi/views/calendar_event_view.xml
odoo_addon_calendar_monthly_multi-16.0.1.0.0.6.dist-info/METADATA
odoo_addon_calendar_monthly_multi-16.0.1.0.0.6.dist-info/WHEEL
odoo_addon_calendar_monthly_multi-16.0.1.0.0.6.dist-info/top_level.txt
odoo_addon_calendar_monthly_multi-16.0.1.0.0.6.dist-info/RECORD
