Metadata-Version: 2.1
Name: odoo-addon-calendar_monthly_multi
Version: 16.0.1.0.0.6
Summary: Calendar Monthly Extension
Home-page: https://github.com/OCA/calendar
Author: Onestein,Odoo Community Association (OCA)
Author-email: support@odoo-community.org
License: AGPL-3
Classifier: Programming Language :: Python
Classifier: Framework :: Odoo
Classifier: Framework :: Odoo :: 16.0
Classifier: License :: OSI Approved :: GNU Affero General Public License v3
Requires-Python: >=3.10
Requires-Dist: odoo<16.1dev,>=16.0a
